signals_notebook/__init__.py
signals_notebook/api.py
signals_notebook/base.py
signals_notebook/common_types.py
signals_notebook/exceptions.py
signals_notebook/item_mapper.py
signals_notebook/jinja_env.py
signals_notebook/attributes/__init__.py
signals_notebook/attributes/attribute.py
signals_notebook/entities/__init__.py
signals_notebook/entities/admin_defined_object.py
signals_notebook/entities/biological_sequence.py
signals_notebook/entities/chemical_drawing.py
signals_notebook/entities/container.py
signals_notebook/entities/contentful_entity.py
signals_notebook/entities/entity.py
signals_notebook/entities/entity_store.py
signals_notebook/entities/excel.py
signals_notebook/entities/experiment.py
signals_notebook/entities/image.py
signals_notebook/entities/materials_table.py
signals_notebook/entities/notebook.py
signals_notebook/entities/power_point.py
signals_notebook/entities/request.py
signals_notebook/entities/spotfire.py
signals_notebook/entities/text.py
signals_notebook/entities/uploaded_resource.py
signals_notebook/entities/word.py
signals_notebook/entities/parallel_experiment/__init__.py
signals_notebook/entities/parallel_experiment/cell.py
signals_notebook/entities/parallel_experiment/parallel_experiment.py
signals_notebook/entities/parallel_experiment/row.py
signals_notebook/entities/parallel_experiment/sub_experiment.py
signals_notebook/entities/parallel_experiment/sub_experiment_layout.py
signals_notebook/entities/parallel_experiment/sub_experiment_summary.py
signals_notebook/entities/plates/__init__.py
signals_notebook/entities/plates/cell.py
signals_notebook/entities/plates/plate_container.py
signals_notebook/entities/plates/plate_row.py
signals_notebook/entities/samples/__init__.py
signals_notebook/entities/samples/cell.py
signals_notebook/entities/samples/sample.py
signals_notebook/entities/samples/samples_container.py
signals_notebook/entities/stoichiometry/__init__.py
signals_notebook/entities/stoichiometry/cell.py
pesn_sdk-1.2.3.dist-info/LICENSE
pesn_sdk-1.2.3.dist-info/METADATA
pesn_sdk-1.2.3.dist-info/NOTICE
pesn_sdk-1.2.3.dist-info/WHEEL
pesn_sdk-1.2.3.dist-info/top_level.txt
pesn_sdk-1.2.3.dist-info/RECORD
