Metadata-Version: 2.1
Name: pesn-sdk
Version: 1.2.3
Summary: Quantori Python SDK for PerkinElmer Signals Notebook
Home-page: https://github.com/quantori/quantori-pesn-python-sdk
Author: Quantori
Author-email: contact@quantori.com
Classifier: Programming Language :: Python :: 3.9
Classifier: Programming Language :: Python :: 3.10
Classifier: License :: OSI Approved :: Apache Software License
Classifier: Operating System :: OS Independent
Requires-Python: >=3.9
License-File: LICENSE
License-File: NOTICE
Requires-Dist: Jinja2 (~=3.1.1)
Requires-Dist: requests (~=2.27)
Requires-Dist: pydantic (==1.10.4)
Requires-Dist: pandas (~=1.4)
Provides-Extra: dev
Requires-Dist: pytest (==6.2.5) ; extra == 'dev'
Requires-Dist: pytest-mock (==3.7.0) ; extra == 'dev'
Requires-Dist: arrow (==1.2.2) ; extra == 'dev'
Requires-Dist: factory-boy (==3.2.1) ; extra == 'dev'
Requires-Dist: pytest-factoryboy (==2.1.0) ; extra == 'dev'
Requires-Dist: pytest-cov (==3.0.0) ; extra == 'dev'
Requires-Dist: mypy (==1.0.0) ; extra == 'dev'
